public static void main(java.lang.String[])
	GETSTATIC java/lang/System out Ljava/io/PrintStream;
	NEW java/lang/StringBuilder
	DUP
	LDC "Foo got run. Class loader: "
	INVOKESPECIAL java/lang/StringBuilder <init>(Ljava/lang/String;)V
	LDC Lorg/de/htwg/klara/Foo;
	INVOKEVIRTUAL java/lang/Class getClassLoader()Ljava/lang/ClassLoader;
	INVOKEVIRTUAL java/lang/StringBuilder append(Ljava/lang/Object;)Ljava/lang/StringBuilder;
	INVOKEVIRTUAL java/lang/StringBuilder toString()Ljava/lang/String;
	INVOKEVIRTUAL java/io/PrintStream println(Ljava/lang/String;)V
	LDC "bla"
	ASTORE 1
	LCONST_0
	LSTORE 2
	ICONST_0
	ISTORE 4
	GOTO FOR1END
FOR1START:
	LLOAD 2
	LDC 2
	LADD
	LSTORE 2
	INC 4 1
FOR1END:
	ILOAD 4
	BIPUSH 10
	IF_ICMPLT FOR1START
	Z14 LLOAD 2
	LDC 2
	LCMP
	IFLE IF1END
	LDC "blub"
	ASTORE 1
IF1END:
	Z17 ALOAD 1
	LDC "a"
	INVOKEVIRTUAL java/lang/String equals(Ljava/lang/Object;)Z
	ISTORE 4
	GETSTATIC java/lang/System out Ljava/io/PrintStream;
	NEW java/lang/StringBuilder
	DUP
	LDC "Result of usless compuation: "
	INVOKESPECIAL java/lang/StringBuilder <init>(Ljava/lang/String;)V
	ILOAD 4
	INVOKEVIRTUAL java/lang/StringBuilder append(Z)Ljava/lang/StringBuilder;
	INVOKEVIRTUAL java/lang/StringBuilder toString()Ljava/lang/String;
	INVOKEVIRTUAL java/io/PrintStream println(Ljava/lang/String;)V
	RETURN